teleser/__init__.py
teleser/bot.py
teleser/executor.py
teleser/messages.py
teleser/validator.py
teleser-0.1.2.dist-info/METADATA
teleser-0.1.2.dist-info/WHEEL
teleser-0.1.2.dist-info/RECORD
