Metadata-Version: 2.1
Name: teleser
Version: 0.1.2
Summary: A Telegram bot for remote command execution with optional user authorization, customizable command validation, and customizable messages.
Author: kai
Author-email: thuan.dv0@gmail.com
Requires-Python: >=3.12,<4.0
Classifier: Programming Language :: Python :: 3
Classifier: Programming Language :: Python :: 3.12
Requires-Dist: nest-asyncio (>=1.6.0,<2.0.0)
Requires-Dist: python-telegram-bot (>=21.4,<22.0)
